nested_cv/__init__.py
nested_cv/nested_cv.py
nested_cv-0.916.dist-info/LICENSE
nested_cv-0.916.dist-info/METADATA
nested_cv-0.916.dist-info/WHEEL
nested_cv-0.916.dist-info/top_level.txt
nested_cv-0.916.dist-info/RECORD
