Metadata-Version: 2.1
Name: nested_cv
Version: 0.916
Summary: A general package to handle nested cross-validation for any estimator that implements the scikit-learn estimator interface.
Home-page: https://github.com/casperbh96/Nested-Cross-Validation
Author-email: ahmedmagdi@outlook.com
Maintainer-email: casperbh.96@gmail.com
License: MIT
Download-URL: https://github.com/user/reponame/archive/v_01.tar.gz
Keywords: ml,xgboost,numpy,scikit-learn,pandas
Platform: UNKNOWN
Classifier: Development Status :: 4 - Beta
Classifier: Intended Audience :: Developers
Classifier: Topic :: Software Development :: Libraries
Classifier: License :: OSI Approved :: MIT License
Classifier: Programming Language :: Python :: 3
Classifier: Programming Language :: Python :: 3.4
Classifier: Programming Language :: Python :: 3.5
Classifier: Programming Language :: Python :: 3.6
Classifier: Programming Language :: Python :: 3.7
